scisave/__init__.py
scisave/ext_json.py
scisave/ext_msgpack.py
scisave/ext_schema.py
scisave/ext_yaml.py
scisave/scisave.py
scisave/version.txt
scisave-1.6.0.dist-info/LICENSE.txt
scisave-1.6.0.dist-info/METADATA
scisave-1.6.0.dist-info/WHEEL
scisave-1.6.0.dist-info/top_level.txt
scisave-1.6.0.dist-info/RECORD
