Metadata-Version: 2.2
Name: scisave
Version: 1.6.0
Summary: SciSave - Serialization for Scientific Data
Author-email: Thomas Guillod <guillod@otvam.ch>
Maintainer-email: Thomas Guillod <guillod@otvam.ch>
License: BSD-2-Clause
Project-URL: Homepage, https://github.com/otvam/scisave
Project-URL: Repository, https://github.com/otvam/scisave
Project-URL: Releases, https://github.com/otvam/scisave/releases
Project-URL: Issues, https://github.com/otvam/scisave/issues
Project-URL: Tags, https://github.com/otvam/scisave/tags
Keywords: Python,Serialization,Deserialization,JSON,YAML,MessagePack,Pickle,NumPy,Schema
Classifier: Development Status :: 5 - Production/Stable
Classifier: License :: OSI Approved :: BSD License
Classifier: Intended Audience :: Science/Research
Classifier: Operating System :: OS Independent
Classifier: Programming Language :: Python :: 3
Classifier: Topic :: Scientific/Engineering
Classifier: Natural Language :: English
Classifier: Environment :: Console
Requires-Python: >=3.9
License-File: LICENSE.txt
Requires-Dist: PyYAML>=6.0
Requires-Dist: numpy>=1.24
Requires-Dist: msgpack>=1.1.0
Requires-Dist: jsonschema>=4.23.0
Provides-Extra: dev
Requires-Dist: pip>=24.3; extra == "dev"
Requires-Dist: build>=1.2; extra == "dev"
Provides-Extra: test
Requires-Dist: ruff>=0.8; extra == "test"
